huaweicloudsdkief/__init__.py
huaweicloudsdkief/v1/__init__.py
huaweicloudsdkief/v1/ief_async_client.py
huaweicloudsdkief/v1/ief_client.py
huaweicloudsdkief/v1/model/__init__.py
huaweicloudsdkief/v1/model/access_config.py
huaweicloudsdkief/v1/model/action.py
huaweicloudsdkief/v1/model/affinity.py
huaweicloudsdkief/v1/model/affinity_node_affinity.py
huaweicloudsdkief/v1/model/affinity_pod_affinity.py
huaweicloudsdkief/v1/model/affinity_pod_anti_affinity.py
huaweicloudsdkief/v1/model/annotations.py
huaweicloudsdkief/v1/model/app.py
huaweicloudsdkief/v1/model/app_configs.py
huaweicloudsdkief/v1/model/app_detail.py
huaweicloudsdkief/v1/model/app_resp.py
huaweicloudsdkief/v1/model/app_response.py
huaweicloudsdkief/v1/model/app_update.py
huaweicloudsdkief/v1/model/app_version_detail.py
huaweicloudsdkief/v1/model/attributes.py
huaweicloudsdkief/v1/model/bach_tags.py
huaweicloudsdkief/v1/model/batch_add_delete_tags_request.py
huaweicloudsdkief/v1/model/batch_add_delete_tags_response.py
huaweicloudsdkief/v1/model/batch_job_for_list.py
huaweicloudsdkief/v1/model/batch_job_request.py
huaweicloudsdkief/v1/model/cert.py
huaweicloudsdkief/v1/model/config_map.py
huaweicloudsdkief/v1/model/config_map_resp.py
huaweicloudsdkief/v1/model/config_maps.py
huaweicloudsdkief/v1/model/configs_map.py
huaweicloudsdkief/v1/model/container_def.py
huaweicloudsdkief/v1/model/container_resp.py
huaweicloudsdkief/v1/model/create_app_request.py
huaweicloudsdkief/v1/model/create_app_response.py
huaweicloudsdkief/v1/model/create_app_versions_request.py
huaweicloudsdkief/v1/model/create_app_versions_response.py
huaweicloudsdkief/v1/model/create_apps_in_deployment_v3.py
huaweicloudsdkief/v1/model/create_batch_job_request.py
huaweicloudsdkief/v1/model/create_batch_job_response.py
huaweicloudsdkief/v1/model/create_config_map_request.py
huaweicloudsdkief/v1/model/create_config_map_response.py
huaweicloudsdkief/v1/model/create_deployments_request.py
huaweicloudsdkief/v1/model/create_deployments_response.py
huaweicloudsdkief-3.1.184.dist-info/METADATA
huaweicloudsdkief-3.1.184.dist-info/WHEEL
huaweicloudsdkief-3.1.184.dist-info/licenses/LICENSE
huaweicloudsdkief-3.1.184.dist-info/RECORD
